exurl/__init__.py
exurl/__main__.py
exurl/split.py
exurl-1.2.dist-info/LICENSE
exurl-1.2.dist-info/METADATA
exurl-1.2.dist-info/WHEEL
exurl-1.2.dist-info/top_level.txt
exurl-1.2.dist-info/RECORD
