Metadata-Version: 2.1
Name: exurl
Version: 1.2
Summary: Division url to many urls approval on parameters - to make fuzzing or testing parameters one by one
Home-page: https://github.com/Abdulrahman-Kamel/exurl
Author: Abdulrahman Kamel
Author-email: vulnabdo@gmail.com
License: MIT
Platform: UNKNOWN
Requires-Dist: urllib3 (>=1.25.9)
